README.md
pygreen.py
setup.py
pygreen.egg-info/PKG-INFO
pygreen.egg-info/SOURCES.txt
pygreen.egg-info/dependency_links.txt
pygreen.egg-info/entry_points.txt
pygreen.egg-info/requires.txt
pygreen.egg-info/top_level.txt