Metadata-Version: 2.1
Name: pygreen
Version: 2.0.3
Summary: A micro static web site generator.
Home-page: https://nicolas-van.github.io/pygreen/
Author: Nicolas Vanhoren
License: UNKNOWN
Project-URL: Bug Reports, https://github.com/nicolas-van/pygreen/issues
Project-URL: Source, https://github.com/nicolas-van/pygreen
Keywords: static website generator
Platform: UNKNOWN
Classifier: Development Status :: 5 - Production/Stable
Classifier: Environment :: Console
Classifier: Intended Audience :: Developers
Classifier: Operating System :: OS Independent
Classifier: Topic :: Internet :: WWW/HTTP :: Dynamic Content
Classifier: License :: OSI Approved :: MIT License
Classifier: Programming Language :: Python :: 2
Classifier: Programming Language :: Python :: 2.7
Classifier: Programming Language :: Python :: 3
Classifier: Programming Language :: Python :: 3.3
Classifier: Programming Language :: Python :: 3.4
Classifier: Programming Language :: Python :: 3.5
Classifier: Programming Language :: Python :: 3.6
Requires-Python: >=2.7, !=3.0.*, !=3.1.*, !=3.2.*, >=3.3
